moclo/kits/__init__.py
moclo/kits/ytk.py
moclo/kits/ytk.version
moclo/registry/__init__.py
moclo/registry/ptk.json.bz2
moclo/registry/ytk.json.bz2
moclo/registry/ytk.py
moclo_ytk-0.4.0.dist-info/LICENSE.txt
moclo_ytk-0.4.0.dist-info/METADATA
moclo_ytk-0.4.0.dist-info/RECORD
moclo_ytk-0.4.0.dist-info/WHEEL
moclo_ytk-0.4.0.dist-info/top_level.txt
moclo_ytk-0.4.0.dist-info/zip-safe
