Metadata-Version: 2.1
Name: moclo-ytk
Version: 0.4.0
Summary: Yeast ToolKit implementation for the base moclo library.
Home-page: https://github.com/althonos/moclo/tree/master/moclo-ytk
Author: Martin Larralde
Author-email: martin.larralde@ens-paris-saclay.fr
License: MIT
Project-URL: Bug Reports, https://github.com/althonos/moclo/issues
Project-URL: Documentation, https://moclo.readthedocs.io/en/latest/kits/ytk/index.html
Project-URL: Addgene Guide, https://www.addgene.org/kits/moclo-ytk/
Keywords: bioinformatics,synthetic biology,modular cloning,moclo,yeast
Platform: any
Classifier: Development Status :: 3 - Alpha
Classifier: Intended Audience :: Science/Research
Classifier: License :: OSI Approved :: MIT License
Classifier: Operating System :: OS Independent
Classifier: Programming Language :: Python
Classifier: Programming Language :: Python :: 2.7
Classifier: Programming Language :: Python :: 3.4
Classifier: Programming Language :: Python :: 3.5
Classifier: Programming Language :: Python :: 3.6
Classifier: Topic :: Scientific/Engineering :: Bio-Informatics
Requires-Python: >= 2.7, != 3.0.*, != 3.1.*, != 3.2.*, != 3.3.*, != 3.5.1
Requires-Dist: moclo (~=0.4.0)
Requires-Dist: six (~=1.10)
